{
    "asset": {
        "format": "jpg",
        "id": "a05225bbdd8bee17e4f4159bed50b1d0",
        "name": "7qbafv.jpg",
        "path": "file:/Users/vasya/Documents/ml/plate/img/7qbafv.jpg",
        "size": {
            "width": 1280,
            "height": 720
        },
        "state": 2,
        "type": 1
    },
    "regions": [
        {
            "id": "JLCd566LH",
            "type": "RECTANGLE",
            "tags": [
                "plate"
            ],
            "boundingBox": {
                "height": 45.701775431861805,
                "width": 69.69222462203024,
                "left": 726.7980561555075,
                "top": 10.780350287907869
            },
            "points": [
                {
                    "x": 726.7980561555075,
                    "y": 10.780350287907869
                },
                {
                    "x": 796.4902807775378,
                    "y": 10.780350287907869
                },
                {
                    "x": 796.4902807775378,
                    "y": 56.48212571976967
                },
                {
                    "x": 726.7980561555075,
                    "y": 56.48212571976967
                }
            ]
        },
        {
            "id": "-D0y6Fm4g",
            "type": "RECTANGLE",
            "tags": [
                "plate"
            ],
            "boundingBox": {
                "height": 32.49760076775432,
                "width": 55.44276457883369,
                "left": 957.8941684665226,
                "top": 60.779150671785025
            },
            "points": [
                {
                    "x": 957.8941684665226,
                    "y": 60.779150671785025
                },
                {
                    "x": 1013.3369330453563,
                    "y": 60.779150671785025
                },
                {
                    "x": 1013.3369330453563,
                    "y": 93.27675143953934
                },
                {
                    "x": 957.8941684665226,
                    "y": 93.27675143953934
                }
            ]
        }
    ],
    "version": "2.1.0"
}